<?xml version="1.0" encoding="UTF-8" standalone="no"?>
<sprite_type>
 <width>70</width>
 <height>90</height>
 <images_list>
  <image_file id="1" file_name="blue_player_1.png"/>
  <image_file id="2" file_name="blue_player_hit_1.png"/>
  <image_file id="3" file_name="blue_player_fire_1.png"/>
 </images_list>
 <animations_list>
  <animation_state>
   <state>IDLE</state>
   <animation_sequence>
    <pose image_id="1" duration="20"/>
   </animation_sequence>
  </animation_state>
  <animation_state>
   <state>HIT</state>
   <animation_sequence>
    <pose image_id="2" duration="10"/>
    <pose image_id="1" duration="10"/>
    <pose image_id="2" duration="10"/>
    <pose image_id="1" duration="10"/>
    <pose image_id="2" duration="10"/>
    <pose image_id="1" duration="10"/>
    <pose image_id="2" duration="10"/>
   </animation_sequence>
  </animation_state>
  <animation_state>
   <state>FIRE</state>
   <animation_sequence>
    <pose image_id="3" duration="10"/>
   </animation_sequence>
  </animation_state>
 </animations_list>  
</sprite_type>